storage_characteriser/StorageCharacteriser.py
storage_characteriser/__init__.py
storage_characteriser/__main__.py
storage_stats/__init__.py
storage_stats/__main__.py
storage_stats/extensionmapping
storage_stats/storagestats.py
storage_stats/data/extensionmapping
storage_stats-0.4.1.dist-info/DESCRIPTION.rst
storage_stats-0.4.1.dist-info/METADATA
storage_stats-0.4.1.dist-info/RECORD
storage_stats-0.4.1.dist-info/WHEEL
storage_stats-0.4.1.dist-info/entry_points.txt
storage_stats-0.4.1.dist-info/metadata.json
storage_stats-0.4.1.dist-info/top_level.txt
storagestats/__init__.py
storagestats/__main__.py
storagestats/storagestats.py
