Metadata-Version: 2.0
Name: storage-stats
Version: 0.4.1
Summary: Calculates count and average file size of files recorded by file extension
Home-page: https://github.com/pmay/storage-stats
Author: Peter May
Author-email: Peter.May@bl.uk
License: Apache Licence 2.0
Platform: UNKNOWN
Classifier: Development Status :: 2 - Pre-Alpha
Classifier: Intended Audience :: End Users/Desktop
Classifier: Topic :: Utilities
Classifier: License :: OSI Approved :: Apache Software License
Classifier: Programming Language :: Python :: 2.7
Requires-Dist: progressbar2 (>=3.6.2)
Requires-Dist: scandir (>=1.2)
